{
  "id": "zhouyi-41",
  "bookId": "zhouyi",
  "order": 41,
  "sectionTitle": "下经",
  "title": "䷨ 损",
  "symbol": "䷨",
  "originalText": "损：有孚，元吉，无咎，可贞，利有攸往？曷之用，二簋可用享。\n彖曰：损，损下益上，其道上行。损而有孚，元吉，无咎，可贞，利有攸往。\n曷之用？二簋可用享；二簋應有时。损剛益柔有时，损益盈虚，与时偕行。\n象曰：山下有澤，损；君子以懲忿窒欲。\n初九：已事遄往，无咎，酌损之。\n象曰：已事遄往，尚合志也。\n九二：利贞，征凶，弗损益之。\n象曰：九二利贞，中以为志也。\n六三：三人行，則损一人；一人行，則得其友。\n象曰：一人行，三則疑也。\n六四：损其疾，使遄有喜，无咎。\n象曰：损其疾，亦可喜也。\n六五：或益之，十朋之龜弗克違，元吉。\n象曰：六五元吉，自上祐也。\n上九：弗损益之，无咎，贞吉，利有攸往，得臣无家。\n象曰：弗损益之，大得志也。",
  "keyExcerpt": "损：有孚，元吉，无咎，可贞，利有攸往？",
  "tags": [
    "顺势",
    "降低内耗",
    "人性",
    "信息差",
    "博弈"
  ],
  "sourceUrl": "https://www.gutenberg.org/ebooks/25501",
  "plainSummary": "这一卦先当作一种状态模型来读：损：有孚，元吉，无咎，可贞，利有攸往？。重点不是预测，而是识别当下处在什么阶段，以及顺势、降低内耗、人性如何变化。",
  "logicNotes": [
    "原文抓手：损：有孚，元吉，无咎，可贞，利有攸往？",
    "理解路径：先还原本章在原书大纲里的位置，再抽取顺势、降低内耗、人性这些可复用模型。",
    "训练目标：学习变化与周期，先训练变化思维，不从算命起卦入门。"
  ],
  "realityMappings": [
    "放到现实里，把一件事看成阶段变化：萌芽、推进、受阻、过盛、转折。策略要跟位置变化，而不是固定一招。",
    "本章可用于复盘一个最近发生的真实场景：你看到的表象是什么，背后的结构、节奏或位置是什么。"
  ],
  "practicePrompt": "平日 10-20 分钟：读完「䷨ 损」后，记录今天一个与「顺势、降低内耗、人性」有关的观察。",
  "oneLineSummary": "损不是少就好，而是把多余和错配减到合适。",
  "translation": {
    "chapterId": "zhouyi-41",
    "title": "䷨ 损",
    "versionNote": "",
    "summary": "损不是单纯失去，而是有时主动减少、节制欲望、减掉错配，让资源按时转到更该承接的位置。",
    "items": [
      {
        "original": "损：有孚，元吉，无咎，可贞，利有攸往？曷之用，二簋可用享。",
        "plain": "损是减少、节制的局面。只要心里真实可信，就大吉、无咎，可以守正，也有利于前往；要用什么来表达诚意，两筐简单的祭品也可以。",
        "keywords": [
          {
            "term": "损",
            "note": "减少、节制、拿掉多余的部分，不只是损失。"
          },
          {
            "term": "有孚",
            "note": "心里有真实可信的诚意，不是表面应付。"
          },
          {
            "term": "可贞",
            "note": "可以守正，但前提是减少得合乎道理。"
          },
          {
            "term": "曷之用",
            "note": "用什么来做这件事，问的是形式和资源多少。"
          },
          {
            "term": "二簋",
            "note": "两筐祭品，表示东西很少但诚意可以足。"
          }
        ]
      },
      {
        "original": "彖曰：损，损下益上，其道上行。损而有孚，元吉，无咎，可贞，利有攸往。",
        "plain": "彖辞说，损是减少下面、增益上面，力量往上走。减少时如果有真实诚信，就大吉、无咎，可以守正，也利于有所前往。",
        "keywords": [
          {
            "term": "损下益上",
            "note": "减少下方的资源或力量，转去补上方。"
          },
          {
            "term": "其道上行",
            "note": "这股变化的方向是向上输送。"
          },
          {
            "term": "损而有孚",
            "note": "减少不是苛扣，而是在真实可信的基础上做取舍。"
          },
          {
            "term": "利有攸往",
            "note": "适合有所行动，不是只停在原地节省。"
          }
        ]
      },
      {
        "original": "曷之用？二簋可用享；二簋應有时。损剛益柔有时，损益盈虚，与时偕行。",
        "plain": "要用什么呢？两筐祭品也可以献上，但这种简薄也要看时机。减少刚强、增益柔顺也有它的时机，减少和增益、满和空，都要跟着时势一起走。",
        "keywords": [
          {
            "term": "二簋可用享",
            "note": "祭品少也可以用来献祭，重点在合时和有诚意。"
          },
          {
            "term": "應有时",
            "note": "应当看时机，不是什么时候都越少越好。"
          },
          {
            "term": "损剛益柔",
            "note": "削减过硬、过强的部分，补足柔和、承接的部分。"
          },
          {
            "term": "损益盈虚",
            "note": "减少和增加、满和空，是会互相转换的状态。"
          },
          {
            "term": "与时偕行",
            "note": "跟着时势一起调整，不固守一种做法。"
          }
        ]
      },
      {
        "original": "象曰：山下有澤，损；君子以懲忿窒欲。",
        "plain": "山下有泽，泽水在山下被收住，这是损的象。君子看到这个象，就克制怒气，堵住过多的欲望。",
        "keywords": [
          {
            "term": "山下有澤",
            "note": "山在上、泽在下，像下方的水被收敛，形成减少和节制。"
          },
          {
            "term": "懲忿",
            "note": "压住怒气，不让情绪直接冲出去。"
          },
          {
            "term": "窒欲",
            "note": "堵住过度欲望，不让想要的东西无限膨胀。"
          }
        ]
      },
      {
        "original": "初九：已事遄往，无咎，酌损之。\n象曰：已事遄往，尚合志也。",
        "plain": "初九把自己的事办完后，就要快点前去帮助上方，这样无咎；但减少多少要斟酌。小象说，这样急往，是因为还能和上面的志向相合。",
        "keywords": [
          {
            "term": "爻",
            "note": "一卦有六爻，像六层台阶，从下往上看事情发展到哪一步。"
          },
          {
            "term": "九",
            "note": "阳爻记号，偏发起、推动、显露；不是吉凶本身。"
          },
          {
            "term": "已事",
            "note": "把自己手上的事处理完。"
          },
          {
            "term": "遄往",
            "note": "迅速前往，不拖延。"
          },
          {
            "term": "酌损",
            "note": "减少要斟酌分寸，不能一下削过头。"
          },
          {
            "term": "合志",
            "note": "彼此目标相合，减少才有正当方向。"
          }
        ]
      },
      {
        "original": "九二：利贞，征凶，弗损益之。\n象曰：九二利贞，中以为志也。",
        "plain": "九二利于守正，贸然出征就凶。不要削损自己去迎合别人，守住中道本身就是对局面的增益。",
        "keywords": [
          {
            "term": "利贞",
            "note": "利于守正，不宜轻易改变立场。"
          },
          {
            "term": "征凶",
            "note": "主动外出征进会有危险。"
          },
          {
            "term": "弗损益之",
            "note": "不靠削损自己来增益对方，守住本位反而有益。"
          },
          {
            "term": "中以为志",
            "note": "把守中、不偏激当作自己的方向。"
          }
        ]
      },
      {
        "original": "六三：三人行，則损一人；一人行，則得其友。\n象曰：一人行，三則疑也。",
        "plain": "六三说，三个人同行，关系太杂，就会损掉一个；一个人前行，反而能得到相合的朋友。小象说，一个人行，是因为三个人在一起就容易生疑。",
        "keywords": [
          {
            "term": "六",
            "note": "阴爻记号，偏承接、缓和、成形；不是被动，也不是吉凶本身。"
          },
          {
            "term": "三人行則损一人",
            "note": "关系过多会互相牵扯，必须减掉一个才清楚。"
          },
          {
            "term": "一人行則得其友",
            "note": "先让自己独立，反而能遇到真正相合的人。"
          },
          {
            "term": "三則疑",
            "note": "三方并行容易互相猜疑，关系不稳。"
          }
        ]
      },
      {
        "original": "六四：损其疾，使遄有喜，无咎。\n象曰：损其疾，亦可喜也。",
        "plain": "六四要减掉自己的毛病，让好转快点出现，就会有喜，无咎。小象说，能减掉病症，本身就值得高兴。",
        "keywords": [
          {
            "term": "损其疾",
            "note": "减掉自己的病痛、毛病或妨碍运行的问题。"
          },
          {
            "term": "使遄有喜",
            "note": "让好消息快点来到，表示问题被及时处理。"
          },
          {
            "term": "无咎",
            "note": "没有后续过失或责难。"
          }
        ]
      },
      {
        "original": "六五：或益之，十朋之龜弗克違，元吉。\n象曰：六五元吉，自上祐也。",
        "plain": "六五会有人来增益它，即使用价值很高的十朋之龟来占，也不能违背这个结果，大吉。小象说，六五的大吉，是从上方得到护佑。",
        "keywords": [
          {
            "term": "或益之",
            "note": "有人来增益、帮助它，不是自己强求来的。"
          },
          {
            "term": "十朋之龜",
            "note": "价值很高的龟，用来表示非常贵重、可信的占验工具。"
          },
          {
            "term": "弗克違",
            "note": "不能违背，表示这个增益挡不住。"
          },
          {
            "term": "元吉",
            "note": "大吉，顺利程度很高。"
          },
          {
            "term": "自上祐",
            "note": "来自上方或更高力量的护佑。"
          }
        ]
      },
      {
        "original": "上九：弗损益之，无咎，贞吉，利有攸往，得臣无家。\n象曰：弗损益之，大得志也。",
        "plain": "上九不再削损下面，却能增益他们，无咎；守正则吉，也利于有所前往。得到臣属却不据为自家私有，小象说，这是志向得到很大实现。",
        "keywords": [
          {
            "term": "弗损益之",
            "note": "不再通过削减别人来增益，而是让对方也得到好处。"
          },
          {
            "term": "得臣无家",
            "note": "得到臣属或支持者，却不把他们当作私人财产。"
          },
          {
            "term": "贞吉",
            "note": "守正才吉，位置高了更要有边界。"
          },
          {
            "term": "大得志",
            "note": "大的志向得以实现，不只是个人得利。"
          }
        ]
      }
    ]
  },
  "logic": {
    "chapterId": "zhouyi-41",
    "notes": [
      {
        "segment": "损：有孚，元吉，无咎，可贞，利有攸往？曷之用，二簋可用享。",
        "model": "损的总模型不是被动亏损，而是主动减掉过量、错配、怒气和欲望，让资源回到合适的位置。它像预算紧张时重新分配资金：少不是目的，诚、时机和尺度才是判断标准。六爻从下往上看变化链：初九快去但要酌量，九二守中不自损迎合，六三关系太杂要减一，六四减病得喜，六五得到上方增益，上九不再损下而转为益人。",
        "example": "一家公司现金吃紧，老板不能简单全员砍薪。按损的模型，先确认真实目标是活下去和保核心交付，再砍掉低转化广告、重复会议、边缘功能和高消耗项目，同时保住客服、研发主线和员工信任。削减能不能成，关键不在砍得多，而在是否真实、合时、分寸对。",
        "summary": "损不是少就好，而是把多余和错配减到合适。",
        "logic": "损的总模型不是被动亏损，而是主动减掉过量、错配、怒气和欲望，让资源回到合适的位置。它像预算紧张时重新分配资金：少不是目的，诚、时机和尺度才是判断标准。六爻从下往上看变化链：初九快去但要酌量，九二守中不自损迎合，六三关系太杂要减一，六四减病得喜，六五得到上方增益，上九不再损下而转为益人。",
        "reality": "一家公司现金吃紧，老板不能简单全员砍薪。按损的模型，先确认真实目标是活下去和保核心交付，再砍掉低转化广告、重复会议、边缘功能和高消耗项目，同时保住客服、研发主线和员工信任。削减能不能成，关键不在砍得多，而在是否真实、合时、分寸对。",
        "practice": [
          "损不是少就好，而是把多余和错配减到合适。"
        ]
      },
      {
        "segment": "彖曰：损，损下益上，其道上行。损而有孚，元吉，无咎，可贞，利有攸往。",
        "model": "彖辞把损的流向说清楚：下方被减少，上方被补足，力量向上走。判断这类调整，先看下方是否真的有过量或可转移的资源，再看上方是否承担更大的职责；如果只是上层索取，下层枯竭，就不是有孚的损。它为后面六爻定边界：初九可以往上助，九二却不能为了迎合而掏空自己。",
        "example": "产品团队把一线客服的反馈时间抽出来给战略项目，如果只是让客服少人少预算，客户投诉会爆。更合理的做法是先用自动化处理重复问题，把省下的人力投入高优先级的缺陷修复，同时公开说明调整目的和效果指标。下方减少必须换来系统上方更有责任的承接。",
        "summary": "资源向上走时，先确认下方不被掏空。",
        "logic": "彖辞把损的流向说清楚：下方被减少，上方被补足，力量向上走。判断这类调整，先看下方是否真的有过量或可转移的资源，再看上方是否承担更大的职责；如果只是上层索取，下层枯竭，就不是有孚的损。它为后面六爻定边界：初九可以往上助，九二却不能为了迎合而掏空自己。",
        "reality": "产品团队把一线客服的反馈时间抽出来给战略项目，如果只是让客服少人少预算，客户投诉会爆。更合理的做法是先用自动化处理重复问题，把省下的人力投入高优先级的缺陷修复，同时公开说明调整目的和效果指标。下方减少必须换来系统上方更有责任的承接。",
        "practice": [
          "资源向上走时，先确认下方不被掏空。"
        ]
      },
      {
        "segment": "曷之用？二簋可用享；二簋應有时。损剛益柔有时，损益盈虚，与时偕行。",
        "model": "这一段补上损的时机规则：简化可以有效，但不能把简化当成永远正确。要看什么时候该减少强硬推进，什么时候该补足柔和承接；满了要减，空了要补，动作随时势变。它连接卦辞的诚意，也解释后面爻辞为什么有的要快往，有的要守中，有的要减关系，有的要受益。",
        "example": "一个 App 想提升留存，团队决定砍功能。按这一段，不是把页面砍到越少越好，而是看数据和阶段：新用户路径太复杂，就减掉弹窗和次要入口；老用户缺少稳定能力，就补足搜索、同步和客服。产品削减要跟使用时机走，不能把极简当口号。",
        "summary": "该减还是该补，要跟时机走。",
        "logic": "这一段补上损的时机规则：简化可以有效，但不能把简化当成永远正确。要看什么时候该减少强硬推进，什么时候该补足柔和承接；满了要减，空了要补，动作随时势变。它连接卦辞的诚意，也解释后面爻辞为什么有的要快往，有的要守中，有的要减关系，有的要受益。",
        "reality": "一个 App 想提升留存，团队决定砍功能。按这一段，不是把页面砍到越少越好，而是看数据和阶段：新用户路径太复杂，就减掉弹窗和次要入口；老用户缺少稳定能力，就补足搜索、同步和客服。产品削减要跟使用时机走，不能把极简当口号。",
        "practice": [
          "该减还是该补，要跟时机走。"
        ]
      },
      {
        "segment": "象曰：山下有澤，损；君子以懲忿窒欲。",
        "model": "大象把损从资源调整拉回到人的内部结构：泽在山下，水被收住，不让它漫出来。现实里最先该损的，常常不是钱和人，而是怒气的外冲、欲望的膨胀、想立刻占有的冲动。它是六爻的心理底盘：没有先收住忿欲，初九会冲过头，九二会讨好，六三会被复杂关系拖住。",
        "example": "一个管理者看到方案被质疑，第一反应是在会上反击。按大象，他先减掉怒气：暂停争辩，记录对方指出的风险，等会后用数据回应；同时减掉想赢下所有讨论的欲望，只保留必须推进的关键决策。情绪被收住，后面的资源削减和关系调整才不会变成报复。",
        "summary": "先减怒气和欲望，再谈减资源。",
        "logic": "大象把损从资源调整拉回到人的内部结构：泽在山下，水被收住，不让它漫出来。现实里最先该损的，常常不是钱和人，而是怒气的外冲、欲望的膨胀、想立刻占有的冲动。它是六爻的心理底盘：没有先收住忿欲，初九会冲过头，九二会讨好，六三会被复杂关系拖住。",
        "reality": "一个管理者看到方案被质疑，第一反应是在会上反击。按大象，他先减掉怒气：暂停争辩，记录对方指出的风险，等会后用数据回应；同时减掉想赢下所有讨论的欲望，只保留必须推进的关键决策。情绪被收住，后面的资源削减和关系调整才不会变成报复。",
        "practice": [
          "先减怒气和欲望，再谈减资源。"
        ]
      },
      {
        "segment": "初九：已事遄往，无咎，酌损之。\n象曰：已事遄往，尚合志也。",
        "model": "初九是损的起点，阳气在最低处，能动但位置还低。它可以快速去帮助上方，前提是自己的事已收好，而且双方目标相合；真正的风险在于热心过头，把自己削到影响本位。它承接总纲的损下益上，但马上加上尺度：能去要快，损多少要酌量。",
        "example": "团队上线前缺测试人手，一个后端工程师已经完成自己模块，可以立刻支援测试和排障。但他不能把后端监控完全放空，也不能替别人承担所有延期责任；更好的做法是安排两小时集中支援，列出自己能覆盖的接口范围。快去是合志，限定投入是酌损。",
        "summary": "能帮就快帮，但别把本位削空。",
        "logic": "初九是损的起点，阳气在最低处，能动但位置还低。它可以快速去帮助上方，前提是自己的事已收好，而且双方目标相合；真正的风险在于热心过头，把自己削到影响本位。它承接总纲的损下益上，但马上加上尺度：能去要快，损多少要酌量。",
        "reality": "团队上线前缺测试人手，一个后端工程师已经完成自己模块，可以立刻支援测试和排障。但他不能把后端监控完全放空，也不能替别人承担所有延期责任；更好的做法是安排两小时集中支援，列出自己能覆盖的接口范围。快去是合志，限定投入是酌损。",
        "practice": [
          "能帮就快帮，但别把本位削空。"
        ]
      },
      {
        "segment": "九二：利贞，征凶，弗损益之。\n象曰：九二利贞，中以为志也。",
        "model": "九二到了下卦中位，重点从初九的快速支援转成守中。这里不适合主动外出表现，也不适合削弱自己去讨好上方；它对全局的益处，恰恰来自保持稳定、专业和边界。它和初九形成对照：初九能支援但要酌量，九二则更要守住中位，不把自损当贡献。",
        "example": "一名财务负责人被业务线要求放松审批，好让季度业绩看起来更好。按九二，他不能为了支持业务就牺牲风控，也不能主动跑去替业务包装数据；他守住预算规则、现金流底线和审批证据，反而是在保护公司。这里的益，不是多做一点，而是不让系统失中。",
        "summary": "不要靠自损迎合别人，守中本身就是贡献。",
        "logic": "九二到了下卦中位，重点从初九的快速支援转成守中。这里不适合主动外出表现，也不适合削弱自己去讨好上方；它对全局的益处，恰恰来自保持稳定、专业和边界。它和初九形成对照：初九能支援但要酌量，九二则更要守住中位，不把自损当贡献。",
        "reality": "一名财务负责人被业务线要求放松审批，好让季度业绩看起来更好。按九二，他不能为了支持业务就牺牲风控，也不能主动跑去替业务包装数据；他守住预算规则、现金流底线和审批证据，反而是在保护公司。这里的益，不是多做一点，而是不让系统失中。",
        "practice": [
          "不要靠自损迎合别人，守中本身就是贡献。"
        ]
      },
      {
        "segment": "六三：三人行，則损一人；一人行，則得其友。\n象曰：一人行，三則疑也。",
        "model": "六三是下卦走到边界的位置，关系和力量开始变杂。这里的损不是削钱，而是减掉不清楚的关系结构：三方并行时，责任、忠诚和判断容易互相牵扯；先退回一个清楚主体，反而能找到真正相合的伙伴。它承接九二的守中：边界守住后，下一步就是把多余关系减清。",
        "example": "一个创业项目同时听投资人、兼职顾问和大客户三方指挥，产品方向每天变。按六三，创始人先取消混乱的三方决策群，只保留内部负责人做最终判断，再分别收集外部建议。关系少了以后，真正愿意承担结果的合伙人反而站出来，团队不再被猜疑拖着走。",
        "summary": "关系太杂时，先减到责任清楚。",
        "logic": "六三是下卦走到边界的位置，关系和力量开始变杂。这里的损不是削钱，而是减掉不清楚的关系结构：三方并行时，责任、忠诚和判断容易互相牵扯；先退回一个清楚主体，反而能找到真正相合的伙伴。它承接九二的守中：边界守住后，下一步就是把多余关系减清。",
        "reality": "一个创业项目同时听投资人、兼职顾问和大客户三方指挥，产品方向每天变。按六三，创始人先取消混乱的三方决策群，只保留内部负责人做最终判断，再分别收集外部建议。关系少了以后，真正愿意承担结果的合伙人反而站出来，团队不再被猜疑拖着走。",
        "practice": [
          "关系太杂时，先减到责任清楚。"
        ]
      },
      {
        "segment": "六四：损其疾，使遄有喜，无咎。\n象曰：损其疾，亦可喜也。",
        "model": "六四进入上卦，是损从下方取舍转到上方修正的阶段。这里要减的是病灶：流程里的堵点、身体里的坏习惯、组织里的反复内耗。它接在六三之后，说明关系减清还不够，还要把真正妨碍运行的问题及时处理；处理得快，喜就来得快。",
        "example": "一个内容团队总是延期，表面看是人手不够，复盘后发现真正病灶是需求入口混乱、反复改题和审批太晚。按六四，负责人不再盲目加人，而是砍掉临时插单，固定选题截止时间，审批超过时限自动顺延。病灶被减掉，团队马上恢复节奏。",
        "summary": "别只减表面成本，要减真正的病灶。",
        "logic": "六四进入上卦，是损从下方取舍转到上方修正的阶段。这里要减的是病灶：流程里的堵点、身体里的坏习惯、组织里的反复内耗。它接在六三之后，说明关系减清还不够，还要把真正妨碍运行的问题及时处理；处理得快，喜就来得快。",
        "reality": "一个内容团队总是延期，表面看是人手不够，复盘后发现真正病灶是需求入口混乱、反复改题和审批太晚。按六四，负责人不再盲目加人，而是砍掉临时插单，固定选题截止时间，审批超过时限自动顺延。病灶被减掉，团队马上恢复节奏。",
        "practice": [
          "别只减表面成本，要减真正的病灶。"
        ]
      },
      {
        "segment": "六五：或益之，十朋之龜弗克違，元吉。\n象曰：六五元吉，自上祐也。",
        "model": "六五是损卦的主位，前面该减的已经减到能承接，局面开始从损转向益。这里的增益不是自己强抢来的，而是因为位置中正、需求真实、系统认可，所以更高处或外部资源自然来补。它承接六四的减病：病灶去掉后，别人给资源才不会被浪费。",
        "example": "一个公益项目先压缩行政开支、公开财务、砍掉效果差的活动，把资源集中到真正能帮助人的服务上。做到这一步后，基金会和政府项目主动追加资助，因为他们看到钱不会被内耗吞掉。增益不是靠哭穷换来的，而是因为系统已经具备承接能力。",
        "summary": "能承接时，外部增益才挡不住。",
        "logic": "六五是损卦的主位，前面该减的已经减到能承接，局面开始从损转向益。这里的增益不是自己强抢来的，而是因为位置中正、需求真实、系统认可，所以更高处或外部资源自然来补。它承接六四的减病：病灶去掉后，别人给资源才不会被浪费。",
        "reality": "一个公益项目先压缩行政开支、公开财务、砍掉效果差的活动，把资源集中到真正能帮助人的服务上。做到这一步后，基金会和政府项目主动追加资助，因为他们看到钱不会被内耗吞掉。增益不是靠哭穷换来的，而是因为系统已经具备承接能力。",
        "practice": [
          "能承接时，外部增益才挡不住。"
        ]
      },
      {
        "segment": "上九：弗损益之，无咎，贞吉，利有攸往，得臣无家。\n象曰：弗损益之，大得志也。",
        "model": "上九是损的收束，也是全卦的反转：走到最高处后，不再靠削下面来补上面，而是让下面也得到增益。回看整条链，损从初九的酌量支援、九二的守中、六三的减杂、六四的减病、六五的受益，最后成熟为不占有、不私用、能让他人一起受益的高位责任。真正的大志，不是把资源收进自己家，而是形成可以共同前往的秩序。",
        "example": "一个部门负责人通过削减无效项目和会议，终于拿到更多预算和高层信任。到上九阶段，他没有继续压榨基层来做个人政绩，而是把新增预算投入工具、培训和合理排班，让团队交付更稳，也让关键成员有成长空间。得到人以后不把人当私产，才是损走到最后的正向结果。",
        "summary": "损到成熟处，是不再损下，而是增益众人。",
        "logic": "上九是损的收束，也是全卦的反转：走到最高处后，不再靠削下面来补上面，而是让下面也得到增益。回看整条链，损从初九的酌量支援、九二的守中、六三的减杂、六四的减病、六五的受益，最后成熟为不占有、不私用、能让他人一起受益的高位责任。真正的大志，不是把资源收进自己家，而是形成可以共同前往的秩序。",
        "reality": "一个部门负责人通过削减无效项目和会议，终于拿到更多预算和高层信任。到上九阶段，他没有继续压榨基层来做个人政绩，而是把新增预算投入工具、培训和合理排班，让团队交付更稳，也让关键成员有成长空间。得到人以后不把人当私产，才是损走到最后的正向结果。",
        "practice": [
          "损到成熟处，是不再损下，而是增益众人。"
        ]
      }
    ]
  }
}
