{
  "chapterId": "zhouyi-29",
  "translation": {
    "chapterId": "zhouyi-29",
    "title": "䷜ 坎",
    "versionNote": "",
    "items": [
      {
        "original": "坎：習坎，有孚，維心亨，行有尚。",
        "plain": "坎是险陷，习坎是重重险陷、反复入坑。处在这样的局面中，要有诚信守住内心，心路先亨通，行动才会有所推重和收获。",
        "keywords": [
          {
            "term": "習坎",
            "note": "重坎、反复遇险，表示危险层层相叠。"
          },
          {
            "term": "有孚",
            "note": "有诚信、可信实，在险中不失内在凭据。"
          },
          {
            "term": "維心亨",
            "note": "内心守正而亨通，是穿过外在险阻的关键。"
          }
        ]
      },
      {
        "original": "彖曰：習坎，重险也。水流而不盈，行险而不失其信。維心亨，乃以剛中也。",
        "plain": "习坎就是重重险阻，像水不断流过坑坎，却不只为填满一处而停滞。能在险中前行而不失信，是因为中间有刚健的主心骨，内心不被险境掏空。",
        "keywords": [
          {
            "term": "重险",
            "note": "险上加险，说明坎卦的难处在于持续、重复、叠加。"
          },
          {
            "term": "水流而不盈",
            "note": "水流过险处而不停滞于填满一坑，象征在险中保持流动和路径。"
          }
        ]
      },
      {
        "original": "行有尚，往有功也。天险不可升也，地险山川丘陵也，王公設险以守其国，坎之时用大矣哉！",
        "plain": "在险中行动仍可贵，因为前往能够成事。天有不可攀升之险，地有山川丘陵之险，王公也会设置险阻守护国家；险不是只带来阻碍，用得合时，也能成为防守和成事的力量。",
        "keywords": [
          {
            "term": "設险",
            "note": "主动设置险阻以守护秩序，说明险也可以被治理和运用。"
          }
        ]
      },
      {
        "original": "象曰：水洊至，習坎；君子以常德行，習教事。",
        "plain": "水一次又一次涌来，是习坎之象。人在反复的险境里，要把德行保持为常，把教化和训练反复练熟；临险时靠的不是一时聪明，而是平日养成的稳定品格和方法。",
        "keywords": [
          {
            "term": "水洊至",
            "note": "水接连到来，象征险情反复出现、压力不断叠加。"
          },
          {
            "term": "常德行",
            "note": "让德行稳定成常，不因险境反复而变形。"
          },
          {
            "term": "習教事",
            "note": "反复练习教化、训练和处事方法，使人在险中有可依循的程序。"
          }
        ]
      },
      {
        "original": "初六：習坎，入于坎窞，凶。\n象曰：習坎入坎，失道凶也。",
        "plain": "初六是阴爻记号，处在重险之初，却又陷入更深的坑中，所以凶。凶不只因为有险，更因为进入险中后失去正道，没有守住可走的路径。",
        "keywords": [
          {
            "term": "六",
            "note": "阴爻记号，偏柔顺、承接、成形；不是好坏本身。"
          },
          {
            "term": "坎窞",
            "note": "坎中更深的陷坑，象征在险中继续下陷。"
          },
          {
            "term": "失道",
            "note": "失去正道和行进路径，是初六由险转凶的关键。"
          }
        ]
      },
      {
        "original": "九二：坎有险，求小得。\n象曰：求小得，未出中也。",
        "plain": "九二是阳爻记号，坎中仍有险，不能奢望一下脱困，只能先求小的所得。它还没有离开险中，但居中不失位，能先保住局部进展。",
        "keywords": [
          {
            "term": "九",
            "note": "阳爻记号，偏刚健、发动、显露；不是吉凶本身。"
          },
          {
            "term": "求小得",
            "note": "在大险未解时先求小成、小得，不冒进求全。"
          }
        ]
      },
      {
        "original": "六三：來之坎坎，险且枕，入于坎窞，勿用。\n象曰：來之坎坎，終无功也。",
        "plain": "六三进来也坎，出去也坎，前后都是险，甚至把险当作枕席贴身相依。再入深坑就不可有所作为，继续动用也终究无功。",
        "keywords": [
          {
            "term": "來之坎坎",
            "note": "来去都遇坎，表示进退皆险、无处不陷。"
          },
          {
            "term": "险且枕",
            "note": "贴着危险而安处，像枕在险上，说明对险已经麻木。"
          }
        ]
      },
      {
        "original": "六四：樽酒簋貳，用缶，納約自牖，終无咎。\n象曰：樽酒簋貳，剛柔際也。",
        "plain": "六四只用一樽酒、两簋饭，甚至用粗朴的瓦器，从窗户送入简约的诚意，最终没有咎。身处险时，刚柔相交，礼物不贵重，贵在简实、守约、能沟通。",
        "keywords": [
          {
            "term": "樽酒簋貳",
            "note": "一樽酒、两簋食，礼物简薄但具备诚意；用缶则强调朴素不尚华饰。"
          },
          {
            "term": "納約自牖",
            "note": "从窗户纳入简约诚意，象征在受限处境中仍找到沟通入口。"
          }
        ]
      },
      {
        "original": "九五：坎不盈，祗既平，无咎。\n象曰：坎不盈，中未大也。",
        "plain": "九五的坑还没有被填满，只是已经接近平稳，所以无咎。它居中得正，却还不能说大成，险势尚未完全消除，仍要谨慎守平。",
        "keywords": [
          {
            "term": "坎不盈",
            "note": "坑坎尚未填满，表示险情还没有彻底解除；只是接近平正，未到大成。"
          }
        ]
      },
      {
        "original": "上六：係用徽纆，寘于叢棘，三歲不得，凶。\n象曰：上六失道，凶三歲也。",
        "plain": "上六被绳索捆系，又被放在丛棘之中，三年不得脱身，凶。它走到重险的尽头仍然失道，结果不只是暂时受困，而是长期被困在惩戒和束缚里。",
        "keywords": [
          {
            "term": "徽纆",
            "note": "捆绑用的绳索，象征拘系和惩罚。"
          },
          {
            "term": "叢棘",
            "note": "荆棘丛，也可指囚禁惩治之地，象征困厄加身。"
          }
        ]
      }
    ]
  },
  "logic": {
    "chapterId": "zhouyi-29",
    "notes": [
      {
        "segment": "坎：習坎，有孚，維心亨，行有尚。",
        "model": "坎卦的总模型是重险：危险不是一次坑洼，而是反复陷入同类困局。可走之道不在于立刻把所有坑填满，而在于像水一样保持方向，凭内心可信的主线继续训练和行动。六爻变化链从初六入深坑而失道开始，九二在险中先求小得，六三进退皆险而勿用，六四用简约诚意打通窗口，九五坑未满而将平，上六失道后被长期捆缚。",
        "example": "一家创业公司连续三个月现金流吃紧，供应商催款、工资日逼近、融资未落地。负责人不能把所有问题一次性填平，而要先守住真实账本和付款优先级，砍掉非必要支出，保住核心客户交付，再用周度现金流训练团队。先求活下来和小回款，等坑接近平，再谈扩张。",
        "summary": "重险中先守住心里的路径，再一步一步穿过去。",
        "logic": "坎卦的总模型是重险：危险不是一次坑洼，而是反复陷入同类困局。可走之道不在于立刻把所有坑填满，而在于像水一样保持方向，凭内心可信的主线继续训练和行动。六爻变化链从初六入深坑而失道开始，九二在险中先求小得，六三进退皆险而勿用，六四用简约诚意打通窗口，九五坑未满而将平，上六失道后被长期捆缚。",
        "reality": "一家创业公司连续三个月现金流吃紧，供应商催款、工资日逼近、融资未落地。负责人不能把所有问题一次性填平，而要先守住真实账本和付款优先级，砍掉非必要支出，保住核心客户交付，再用周度现金流训练团队。先求活下来和小回款，等坑接近平，再谈扩张。",
        "practice": [
          "重险中先守住心里的路径，再一步一步穿过去。"
        ]
      },
      {
        "segment": "彖曰：習坎，重险也。水流而不盈，行险而不失其信。維心亨，乃以剛中也。",
        "model": "彖辞把坎的机制说成水行重险：水经过坑坎，不把自己耗在填满每一个坑上，也不因坑深而改掉流向。六爻链按这个原则展开，初六失去流向而下陷，九二保住中线所以能得小成果，六三被险困住而不能动，六四以简约连接恢复通路，九五险坑将平但未大成，上六失信失道后被困死。",
        "example": "线上支付系统连续故障，团队若执着于当天修完所有历史架构债，只会扩大事故。更稳的做法是先确认交易一致性、开只读保护、恢复核心支付链路，保留用户通知和审计记录。事故未彻底解除前，团队靠事实、值班节奏和回滚纪律保持可信。",
        "summary": "过险不是填平所有坑，而是不丢方向和可信度。",
        "logic": "彖辞把坎的机制说成水行重险：水经过坑坎，不把自己耗在填满每一个坑上，也不因坑深而改掉流向。六爻链按这个原则展开，初六失去流向而下陷，九二保住中线所以能得小成果，六三被险困住而不能动，六四以简约连接恢复通路，九五险坑将平但未大成，上六失信失道后被困死。",
        "reality": "线上支付系统连续故障，团队若执着于当天修完所有历史架构债，只会扩大事故。更稳的做法是先确认交易一致性、开只读保护、恢复核心支付链路，保留用户通知和审计记录。事故未彻底解除前，团队靠事实、值班节奏和回滚纪律保持可信。",
        "practice": [
          "过险不是填平所有坑，而是不丢方向和可信度。"
        ]
      },
      {
        "segment": "行有尚，往有功也。天险不可升也，地险山川丘陵也，王公設险以守其国，坎之时用大矣哉！",
        "model": "这一段把坎从被动遇险推到主动用险：险可以困人，也可以成为边界和防线。六爻链中，初六和六三是被险吞没，九二是在险中保住小进展，六四开始把受限处境转成沟通入口，九五把险势压到将平，上六则说明失道者会被制度性险阻长期约束。坎的成熟用法，是让险守住秩序，而不是让险拖垮行动。",
        "example": "公司做资金审批，以前所有付款都追求速度，结果出现重复打款和虚假供应商。新的制度把大额付款、陌生账户和关联交易设置成必须复核的关口。这个险不是为难业务，而是让现金流在高风险处自动减速，避免一次错误把公司拖进深坑。",
        "summary": "险用得正，就从陷阱变成防线。",
        "logic": "这一段把坎从被动遇险推到主动用险：险可以困人，也可以成为边界和防线。六爻链中，初六和六三是被险吞没，九二是在险中保住小进展，六四开始把受限处境转成沟通入口，九五把险势压到将平，上六则说明失道者会被制度性险阻长期约束。坎的成熟用法，是让险守住秩序，而不是让险拖垮行动。",
        "reality": "公司做资金审批，以前所有付款都追求速度，结果出现重复打款和虚假供应商。新的制度把大额付款、陌生账户和关联交易设置成必须复核的关口。这个险不是为难业务，而是让现金流在高风险处自动减速，避免一次错误把公司拖进深坑。",
        "practice": [
          "险用得正，就从陷阱变成防线。"
        ]
      },
      {
        "segment": "象曰：水洊至，習坎；君子以常德行，習教事。",
        "model": "大象把重险落到训练：水反复到来，人也要把稳定德行和处事方法练成常态。六爻链显示训练不足就会像初六一样入深坑，训练尚在时只能像九二先求小得，遇到六三的进退皆险要停用，六四靠朴素流程恢复连接，九五靠持续守平脱离大险，上六则是长期不训练、不守道后的困锁结果。",
        "example": "安全团队不能等被攻击后才写流程。平时要反复演练密钥轮换、权限回收、告警分级、客户通知和法务升级路径。真正事故来时，大家按训练先隔离凭证、保全日志、恢复关键服务，而不是在群里争谁负责。常态训练让反复危险变成可执行步骤。",
        "summary": "反复遇险的人，靠平日练熟的路脱险。",
        "logic": "大象把重险落到训练：水反复到来，人也要把稳定德行和处事方法练成常态。六爻链显示训练不足就会像初六一样入深坑，训练尚在时只能像九二先求小得，遇到六三的进退皆险要停用，六四靠朴素流程恢复连接，九五靠持续守平脱离大险，上六则是长期不训练、不守道后的困锁结果。",
        "reality": "安全团队不能等被攻击后才写流程。平时要反复演练密钥轮换、权限回收、告警分级、客户通知和法务升级路径。真正事故来时，大家按训练先隔离凭证、保全日志、恢复关键服务，而不是在群里争谁负责。常态训练让反复危险变成可执行步骤。",
        "practice": [
          "反复遇险的人，靠平日练熟的路脱险。"
        ]
      },
      {
        "segment": "初六：習坎，入于坎窞，凶。\n象曰：習坎入坎，失道凶也。",
        "model": "初六是坎卦变化链的第一凶：外面已经是重险，里面又掉进更深的坑，关键不是坑深本身，而是失去可走的道路。它若不能马上止住下陷，就到不了九二的小得、六四的沟通和九五的将平，只会提前滑向上六的长期拘困。坎的第一课，是先找回路径，不要在慌乱中继续加深坑。",
        "example": "公司现金流断裂后，负责人为了遮掩缺口继续借高息短贷、拖欠税款、虚报回款。表面是在救急，实际把财务账、信用和法律边界都打乱。此时最重要的不是再找一个临时窟窿，而是停掉新增承诺，做真实现金表，列出必须支付和可谈判延期的清单。",
        "summary": "入险后先别加深坑，失去路径才是真凶。",
        "logic": "初六是坎卦变化链的第一凶：外面已经是重险，里面又掉进更深的坑，关键不是坑深本身，而是失去可走的道路。它若不能马上止住下陷，就到不了九二的小得、六四的沟通和九五的将平，只会提前滑向上六的长期拘困。坎的第一课，是先找回路径，不要在慌乱中继续加深坑。",
        "reality": "公司现金流断裂后，负责人为了遮掩缺口继续借高息短贷、拖欠税款、虚报回款。表面是在救急，实际把财务账、信用和法律边界都打乱。此时最重要的不是再找一个临时窟窿，而是停掉新增承诺，做真实现金表，列出必须支付和可谈判延期的清单。",
        "practice": [
          "入险后先别加深坑，失去路径才是真凶。"
        ]
      },
      {
        "segment": "九二：坎有险，求小得。\n象曰：求小得，未出中也。",
        "model": "九二处在重险中段，还没有出险，却比初六多了一条居中的路径。变化链到这里，目标不能设成一次性脱困，而是先拿到小得：一笔回款、一段恢复链路、一个可复核事实、一个稳定窗口。小得不是小气，而是在六三的进退皆险到来前稳住中线，为六四沟通和九五将平积累条件。",
        "example": "数据库迁移失败后，用户登录和订单查询都受影响。团队不应立即重做全量迁移，而是先恢复只读查询、冻结写入扩散、找回最近一致备份，再让高价值客户能查订单。系统仍在险中，但每个小恢复都减少混乱，给后续修复争取时间。",
        "summary": "未出险时，先求能稳住局面的小成果。",
        "logic": "九二处在重险中段，还没有出险，却比初六多了一条居中的路径。变化链到这里，目标不能设成一次性脱困，而是先拿到小得：一笔回款、一段恢复链路、一个可复核事实、一个稳定窗口。小得不是小气，而是在六三的进退皆险到来前稳住中线，为六四沟通和九五将平积累条件。",
        "reality": "数据库迁移失败后，用户登录和订单查询都受影响。团队不应立即重做全量迁移，而是先恢复只读查询、冻结写入扩散、找回最近一致备份，再让高价值客户能查订单。系统仍在险中，但每个小恢复都减少混乱，给后续修复争取时间。",
        "practice": [
          "未出险时，先求能稳住局面的小成果。"
        ]
      },
      {
        "segment": "六三：來之坎坎，险且枕，入于坎窞，勿用。\n象曰：來之坎坎，終无功也。",
        "model": "六三是坎卦变化链的停用点：往前是险，退回也是险，甚至已经把危险当成日常依靠。它承接初六的失道和九二的小得不足，一旦继续动用，就会再入深坑。这里的正确动作不是逞强推进，而是暂停、隔离、减载，等待六四那种简约而真实的沟通入口出现。",
        "example": "一个业务线增长停滞，继续投广告会烧现金，停止投放又会丢掉渠道排名；降价伤毛利，涨价掉客户。负责人若在每个方向都带坑时继续加码，只会扩大亏损。更好的做法是暂停扩张预算，保住老客户服务，做小样本定价测试，先不要把全公司资源压上去。",
        "summary": "进退都是坑时，最该做的是暂停动用。",
        "logic": "六三是坎卦变化链的停用点：往前是险，退回也是险，甚至已经把危险当成日常依靠。它承接初六的失道和九二的小得不足，一旦继续动用，就会再入深坑。这里的正确动作不是逞强推进，而是暂停、隔离、减载，等待六四那种简约而真实的沟通入口出现。",
        "reality": "一个业务线增长停滞，继续投广告会烧现金，停止投放又会丢掉渠道排名；降价伤毛利，涨价掉客户。负责人若在每个方向都带坑时继续加码，只会扩大亏损。更好的做法是暂停扩张预算，保住老客户服务，做小样本定价测试，先不要把全公司资源压上去。",
        "practice": [
          "进退都是坑时，最该做的是暂停动用。"
        ]
      },
      {
        "segment": "六四：樽酒簋貳，用缶，納約自牖，終无咎。\n象曰：樽酒簋貳，剛柔際也。",
        "model": "六四是坎卦变化链的恢复连接点：经历初六下陷、九二小得、六三停用之后，局面还在险中，但可以用很简约、很真实的方式从窗口建立约定。这里不靠盛大仪式和复杂方案，而靠刚柔交接时能被对方接住的事实、承诺和入口。它为九五的将平创造条件，也避免滑向上六的封闭拘困。",
        "example": "数据泄露事故发生后，公司无法马上给客户完整根因报告。负责人可以先通过正式状态页和客户经理发出简明承诺：受影响范围、已采取隔离措施、下一次更新时间、补救联系人。信息不华丽，但真实、可兑现、有入口，比沉默或堆砌公关话术更能避免二次伤害。",
        "summary": "险中沟通贵在简实守约，不在排场。",
        "logic": "六四是坎卦变化链的恢复连接点：经历初六下陷、九二小得、六三停用之后，局面还在险中，但可以用很简约、很真实的方式从窗口建立约定。这里不靠盛大仪式和复杂方案，而靠刚柔交接时能被对方接住的事实、承诺和入口。它为九五的将平创造条件，也避免滑向上六的封闭拘困。",
        "reality": "数据泄露事故发生后，公司无法马上给客户完整根因报告。负责人可以先通过正式状态页和客户经理发出简明承诺：受影响范围、已采取隔离措施、下一次更新时间、补救联系人。信息不华丽，但真实、可兑现、有入口，比沉默或堆砌公关话术更能避免二次伤害。",
        "practice": [
          "险中沟通贵在简实守约，不在排场。"
        ]
      },
      {
        "segment": "九五：坎不盈，祗既平，无咎。\n象曰：坎不盈，中未大也。",
        "model": "九五是坎卦变化链的接近平稳：坑还没有填满，危险还没有彻底消失，但局面已经从初六的失道、六三的进退皆险，走到可守中线的平处。这里最怕把将平当成大成，提前撤掉训练、预算和监控。九五的无咎来自继续守平，等水位真正稳定，而不是宣布险情结束。",
        "example": "公司通过裁撤非核心项目、追回应收款和延期债务，把现金 runway 从三周拉到四个月。局面接近平，但欠款、客户流失和士气仍未恢复。管理层可以恢复部分投入，却不能马上重启大规模招聘和营销；仍要每周看现金表、客户续约和关键岗位负荷。",
        "summary": "坑将平时别庆功，继续守到真正稳定。",
        "logic": "九五是坎卦变化链的接近平稳：坑还没有填满，危险还没有彻底消失，但局面已经从初六的失道、六三的进退皆险，走到可守中线的平处。这里最怕把将平当成大成，提前撤掉训练、预算和监控。九五的无咎来自继续守平，等水位真正稳定，而不是宣布险情结束。",
        "reality": "公司通过裁撤非核心项目、追回应收款和延期债务，把现金 runway 从三周拉到四个月。局面接近平，但欠款、客户流失和士气仍未恢复。管理层可以恢复部分投入，却不能马上重启大规模招聘和营销；仍要每周看现金表、客户续约和关键岗位负荷。",
        "practice": [
          "坑将平时别庆功，继续守到真正稳定。"
        ]
      },
      {
        "segment": "上六：係用徽纆，寘于叢棘，三歲不得，凶。\n象曰：上六失道，凶三歲也。",
        "model": "上六是坎卦变化链的最坏结局：前面本可在初六找回路径，在九二求小得，在六三停用，在六四建立简约约定，在九五守到将平；若一路失道，最后危险变成外部强制拘束，绳索和丛棘都意味着长期不能自由行动。坎到这里不再是穿越危险，而是被危险和惩戒共同锁住。",
        "example": "企业多年忽视数据合规，事故后又隐瞒范围、删除日志、拖延通知。监管介入后，公司被罚款、限制业务、接受长期审计，关键负责人被追责。此时再说优化流程已经太晚，因为失道把普通技术事故变成制度性束缚，恢复自由需要几年。",
        "summary": "反复失道，险境最终会变成长期束缚。",
        "logic": "上六是坎卦变化链的最坏结局：前面本可在初六找回路径，在九二求小得，在六三停用，在六四建立简约约定，在九五守到将平；若一路失道，最后危险变成外部强制拘束，绳索和丛棘都意味着长期不能自由行动。坎到这里不再是穿越危险，而是被危险和惩戒共同锁住。",
        "reality": "企业多年忽视数据合规，事故后又隐瞒范围、删除日志、拖延通知。监管介入后，公司被罚款、限制业务、接受长期审计，关键负责人被追责。此时再说优化流程已经太晚，因为失道把普通技术事故变成制度性束缚，恢复自由需要几年。",
        "practice": [
          "反复失道，险境最终会变成长期束缚。"
        ]
      }
    ]
  },
  "oneLineSummary": "重险中先守住心里的路径，再一步一步穿过去。"
}
