{
  "id": "ddj-53",
  "bookId": "dao-de-jing",
  "order": 53,
  "sectionTitle": "德经",
  "title": "第53章",
  "symbol": "德",
  "originalText": "使我介然有知，行于大道，唯施是畏。大道甚夷，而人好徑。朝甚除，田\n甚蕪，倉甚虚；服文采，帶利劍，厭飲食，财货有餘；是为盗夸。非道也\n哉！",
  "keyExcerpt": "使我介然有知，行于大道，唯施是畏。",
  "tags": [
    "顺势",
    "降低内耗",
    "人性",
    "信息差",
    "博弈"
  ],
  "sourceUrl": "https://www.gutenberg.org/ebooks/7337",
  "plainSummary": "这一章可以先当作世界运行方式的提示来读：使我介然有知，行于大道，唯施是畏。。它提醒你先看清力量流向，再决定是否出手，核心落在顺势、降低内耗、人性。",
  "logicNotes": [
    "原文抓手：使我介然有知，行于大道，唯施是畏。",
    "理解路径：先还原本章在原书大纲里的位置，再抽取顺势、降低内耗、人性这些可复用模型。",
    "训练目标：建立底层世界观，降低内耗，学会顺势与借力。"
  ],
  "realityMappings": [
    "放到生活里，先观察自己是否在用意志硬扛系统阻力：情绪、关系、工作流程、欲望刺激，哪一个正在制造内耗。",
    "本章可用于复盘一个最近发生的真实场景：你看到的表象是什么，背后的结构、节奏或位置是什么。"
  ],
  "practicePrompt": "平日 10-20 分钟：读完「第53章」后，记录今天一个与「顺势、降低内耗、人性」有关的观察。",
  "oneLineSummary": "别被体面带走，先查这条捷径是不是在掏空底盘。",
  "translation": {
    "chapterId": "ddj-53",
    "title": "道德经 第53章",
    "versionNote": "Project Gutenberg 此章作“而人好徑”，按 Wikisource 王弼本校为“而民好径”。",
    "items": [
      {
        "original": "使我介然有知，行于大道，唯施是畏。大道甚夷，而民好径。朝甚除，田甚芜，仓甚虚；服文彩，带利剑，厌饮食，财货有馀；是为盗夸。非道也哉！",
        "plain": "如果我真的懂一点道，走在大道上，最怕偏到旁门小路。路本来平直，人却爱走捷径；宫殿很干净，田地荒了，仓库空了，少数人还穿好衣、佩利剑、吃喝过度、钱货有余，这就是披着体面的抢夺。",
        "keywords": [
          {
            "term": "介然",
            "note": "稍微有一点。"
          },
          {
            "term": "施",
            "note": "偏斜，偏离正路。"
          },
          {
            "term": "甚夷",
            "note": "很平坦。"
          },
          {
            "term": "径",
            "note": "小路、捷径。"
          },
          {
            "term": "朝甚除",
            "note": "宫室收拾得很整洁。"
          },
          {
            "term": "盗夸",
            "note": "靠掠夺来炫耀。"
          }
        ]
      }
    ]
  },
  "logic": {
    "chapterId": "ddj-53",
    "notes": [
      {
        "segment": "使我介然有知，行于大道，唯施是畏。大道甚夷，而民好径。朝甚除，田甚芜，仓甚虚；服文彩，带利剑，厌饮食，财货有馀；是为盗夸。非道也哉！",
        "logic": "捷径常见的样子，是让显眼处变体面，让基础处被掏空。用这一章时，别只看**体面**，要看钱、人、时间从哪里来：如果前台越光鲜，田地、仓库、基层越空，这条**捷径**就是换了包装的**掠夺**。",
        "reality": "问题：公司大做品牌发布会，老板说这是快速起势。怎么用模型看：发布会很**体面**，但供应商款拖着、客服被裁、研发预算被挪走。光鲜来自压榨底盘，这不是增长，是体面的**掠夺**。",
        "practice": [
          "别被**体面**带走，先查这条**捷径**是不是在掏空底盘。"
        ]
      }
    ]
  }
}
