{
  "id": "ddj-49",
  "bookId": "dao-de-jing",
  "order": 49,
  "sectionTitle": "德经",
  "title": "第49章",
  "symbol": "德",
  "originalText": "圣人常无心，以百姓心为心。善者，吾善之；不善者，吾亦善之；德善。\n信者，吾信之；不信者，吾亦信之；德信。圣人在天下，歙歙焉，为天下\n渾其心，百姓皆注其耳目，圣人皆孩之。",
  "keyExcerpt": "圣人常无心，以百姓心为心。",
  "tags": [
    "顺势",
    "人性",
    "系统规律",
    "时位"
  ],
  "sourceUrl": "https://www.gutenberg.org/ebooks/7337",
  "plainSummary": "这一章可以先当作世界运行方式的提示来读：圣人常无心，以百姓心为心。。它提醒你先看清力量流向，再决定是否出手，核心落在顺势、人性、系统规律。",
  "logicNotes": [
    "原文抓手：圣人常无心，以百姓心为心。",
    "理解路径：先还原本章在原书大纲里的位置，再抽取顺势、人性、系统规律这些可复用模型。",
    "训练目标：建立底层世界观，降低内耗，学会顺势与借力。"
  ],
  "realityMappings": [
    "放到生活里，先观察自己是否在用意志硬扛系统阻力：情绪、关系、工作流程、欲望刺激，哪一个正在制造内耗。",
    "本章可用于复盘一个最近发生的真实场景：你看到的表象是什么，背后的结构、节奏或位置是什么。"
  ],
  "practicePrompt": "周末复盘：把这一周的一个案例放进「第49章」里，看它体现了哪些标签：顺势、人性、系统规律。",
  "oneLineSummary": "放下私心和死标签，用一致规则对人。",
  "translation": {
    "chapterId": "ddj-49",
    "title": "道德经 第49章",
    "versionNote": "",
    "items": [
      {
        "original": "圣人常无心，以百姓心为心。善者，吾善之；不善者，吾亦善之；德善。信者，吾信之；不信者，吾亦信之；德信。圣人在天下，歙歙焉，为天下渾其心，百姓皆注其耳目，圣人皆孩之。",
        "plain": "圣人不把自己的想法摆在最前面，而是把百姓的心当成自己的心。善的人善待，不善的人也善待；可信的人相信，不可信的人也用信来对待，让人心不被搅乱，像照看孩子一样对待百姓。",
        "keywords": [
          {
            "term": "常无心",
            "note": "没有固定私心。"
          },
          {
            "term": "以百姓心为心",
            "note": "把百姓的心当成自己的心。"
          },
          {
            "term": "德善 / 德信",
            "note": "真正厚实的善和信。"
          },
          {
            "term": "歙歙焉",
            "note": "收敛、不张扬的样子。"
          },
          {
            "term": "渾其心",
            "note": "让人心朴厚，不分裂。"
          },
          {
            "term": "孩之",
            "note": "像对孩子一样看待。"
          }
        ]
      }
    ]
  },
  "logic": {
    "chapterId": "ddj-49",
    "notes": [
      {
        "segment": "圣人常无心，以百姓心为心。善者，吾善之；不善者，吾亦善之；德善。信者，吾信之；不信者，吾亦信之；德信。圣人在天下，歙歙焉，为天下渾其心，百姓皆注其耳目，圣人皆孩之。",
        "logic": "对人不能只凭自己的喜恶，也不能给人贴死标签。用这一章时，先放下**私心**和**死标签**，再用同一套规则看事实、给机会、设边界。",
        "reality": "问题：一个同事以前经常迟到，大家默认他“不靠谱”。怎么用模型看：先别让**死标签**决定一切；给他同样的排班规则、提醒机制和迟到后果。守规则就继续合作，反复破坏就按规则处理。",
        "practice": [
          "放下**私心**和**死标签**，用一致**规则**对人。"
        ]
      }
    ]
  }
}
